scenic/.DS_Store
scenic/__init__.py
scenic/__main__.py
scenic/core/.DS_Store
scenic/core/__init__.py
scenic/core/distributions.py
scenic/core/errors.py
scenic/core/external_params.py
scenic/core/geometry.py
scenic/core/lazy_eval.py
scenic/core/object_types.py
scenic/core/propositions.py
scenic/core/pruning.py
scenic/core/regions.py
scenic/core/requirements.py
scenic/core/sample_checking.py
scenic/core/scenarios.py
scenic/core/sensors.py
scenic/core/serialization.py
scenic/core/shapes.py
scenic/core/simulators.py
scenic/core/specifiers.py
scenic/core/type_support.py
scenic/core/utils.py
scenic/core/vectors.py
scenic/core/visibility.py
scenic/core/workspaces.py
scenic/core/dynamics/__init__.py
scenic/core/dynamics/actions.py
scenic/core/dynamics/behaviors.py
scenic/core/dynamics/guards.py
scenic/core/dynamics/invocables.py
scenic/core/dynamics/scenarios.py
scenic/core/dynamics/utils.py
scenic/core/type_support/.DS_Store
scenic/domains/.DS_Store
scenic/domains/__init__.py
scenic/domains/driving/__init__.py
scenic/domains/driving/actions.py
scenic/domains/driving/behaviors.scenic
scenic/domains/driving/controllers.py
scenic/domains/driving/model.scenic
scenic/domains/driving/roads.py
scenic/domains/driving/simulators.py
scenic/domains/driving/workspace.py
scenic/formats/.DS_Store
scenic/formats/__init__.py
scenic/formats/opendrive/__init__.py
scenic/formats/opendrive/workspace.py
scenic/formats/opendrive/xodr_parser.py
scenic/simulators/.DS_Store
scenic/simulators/__init__.py
scenic/simulators/carla/.DS_Store
scenic/simulators/carla/__init__.py
scenic/simulators/carla/actions.py
scenic/simulators/carla/behaviors.scenic
scenic/simulators/carla/blueprints.py
scenic/simulators/carla/misc.py
scenic/simulators/carla/model.scenic
scenic/simulators/carla/sensors.py
scenic/simulators/carla/simulator.py
scenic/simulators/carla/utils/utils.py
scenic/simulators/carla/utils/visuals.py
scenic/simulators/gta/.DS_Store
scenic/simulators/gta/__init__.py
scenic-3.1.0.dist-info/entry_points.txt
scenic-3.1.0.dist-info/licenses/LICENSE
scenic-3.1.0.dist-info/WHEEL
scenic-3.1.0.dist-info/METADATA
scenic-3.1.0.dist-info/RECORD
