Metadata-Version: 2.4
Name: scenic
Version: 3.1.0
Summary: The Scenic scenario description language.
Author: Daniel Fremont, Eric Vin, Shun Kashiwa, Edward Kim, Tommaso Dreossi, Shromona Ghosh, Xiangyu Yue, Alberto L. Sangiovanni-Vincentelli, Sanjit A. Seshia
Maintainer-email: Daniel Fremont <dfremont@ucsc.edu>
Requires-Python: >=3.8
Classifier: Operating System :: OS Independent
Classifier: Development Status :: 5 - Production/Stable
Classifier: License :: OSI Approved :: BSD License
Classifier: Programming Language :: Python :: 3
License-File: LICENSE
Requires-Dist: antlr4-python3-runtime ~= 4.11
Requires-Dist: attrs >= 19.3.0
Requires-Dist: dotmap ~= 1.3
Requires-Dist: mapbox_earcut >= 0.12.10
Requires-Dist: matplotlib ~= 3.2
Requires-Dist: manifold3d >= 2.5.1
Requires-Dist: networkx >= 2.6
Requires-Dist: numpy >= 1.24
Requires-Dist: opencv-python ~= 4.5
Requires-Dist: pegen >= 0.3.0
Requires-Dist: pillow >= 9.1
Requires-Dist: pygame >= 2.1.3.dev8, <3; python_version >= "3.11"
Requires-Dist: pygame ~= 2.0; python_version < "3.11"
Requires-Dist: pyglet >= 1.5, <= 1.5.26
Requires-Dist: python-fcl >= 0.7
Requires-Dist: Rtree ~= 1.0
Requires-Dist: rv-ltl ~= 0.1
Requires-Dist: scikit-image ~= 0.21
Requires-Dist: scipy ~= 1.7
Requires-Dist: shapely ~= 2.0
Requires-Dist: trimesh >=4.6.0, <5
Requires-Dist: scenic[test-full] ; extra == "dev"
Requires-Dist: black ~= 25.1.0 ; extra == "dev"
Requires-Dist: isort ~= 5.12.0 ; extra == "dev"
Requires-Dist: pre-commit ~= 3.0 ; extra == "dev"
Requires-Dist: pytest-cov >= 3.0.0 ; extra == "dev"
Requires-Dist: tox ~= 4.0 ; extra == "dev"
Requires-Dist: pyproj ~= 3.0 ; extra == "guideways" and ( python_version < "3.10")
Requires-Dist: pyproj ~= 3.3 ; extra == "guideways" and ( python_version >= "3.10")
Requires-Dist: metadrive-simulator >= 0.4.3 ; extra == "metadrive"
Requires-Dist: sumolib >= 1.21.0 ; extra == "metadrive"
Requires-Dist: pytest >= 7.0.0, <9 ; extra == "test"
Requires-Dist: pytest-cov >= 3.0.0 ; extra == "test"
Requires-Dist: pytest-randomly ~= 3.2 ; extra == "test"
Requires-Dist: scenic[test] ; extra == "test-full"
Requires-Dist: scenic[guideways] ; extra == "test-full"
Requires-Dist: scenic[metadrive] ; extra == "test-full" and ( python_version < "3.12")
Requires-Dist: astor >= 0.8.1 ; extra == "test-full"
Requires-Dist: carla >= 0.9.12 ; extra == "test-full" and ( python_version <= "3.10" and (platform_system == "Linux" or platform_system == "Windows"))
Requires-Dist: dill ; extra == "test-full"
Requires-Dist: exceptiongroup ; extra == "test-full"
Requires-Dist: inflect ~= 5.5 ; extra == "test-full"
Requires-Dist: pygments ~= 2.11 ; extra == "test-full"
Requires-Dist: sphinx >= 6.2.0, <7.2.0 ; extra == "test-full"
Requires-Dist: sphinx_rtd_theme >= 0.5.2 ; extra == "test-full"
Requires-Dist: sphinx-tabs ~= 3.4.1 ; extra == "test-full"
Requires-Dist: verifai >= 2.1.0b1 ; extra == "test-full"
Project-URL: Documentation, https://docs.scenic-lang.org
Project-URL: Homepage, https://scenic-lang.org/
Project-URL: Repository, https://github.com/BerkeleyLearnVerify/Scenic
Provides-Extra: dev
Provides-Extra: guideways
Provides-Extra: metadrive
Provides-Extra: test
Provides-Extra: test-full
